dynlab/__init__.py
dynlab/flows.py
dynlab/utils.py
dynlab/diagnostics/__init__.py
dynlab/diagnostics/_base_classes.py
dynlab/diagnostics/eulerian.py
dynlab/diagnostics/lagrangian.py
dynlab-0.1.0.dist-info/METADATA
dynlab-0.1.0.dist-info/WHEEL
dynlab-0.1.0.dist-info/licenses/LICENSE
dynlab-0.1.0.dist-info/RECORD
